{
    "/js/app.js": "/js/app.js",
    "/css/app.css": "/css/app.css",
    "/css/sidebar-1.css": "/css/sidebar-1.css",
    "/css/sidebar.css": "/css/sidebar.css",
    "/css/Pretty-Registration-Form.css": "/css/Pretty-Registration-Form.css",
    "/css/News-Cards.css": "/css/News-Cards.css",
    "/css/custom.css": "/css/custom.css",
    "/css/Customizable-Background--Overlay.css": "/css/Customizable-Background--Overlay.css",
    "/css/dh-card-image-left-dark.css": "/css/dh-card-image-left-dark.css"
}
